annotation_validation/__init__.py
annotation_validation/annotation_validation.py
annotation_validation-0.1.1.dist-info/AUTHORS.rst
annotation_validation-0.1.1.dist-info/LICENSE
annotation_validation-0.1.1.dist-info/METADATA
annotation_validation-0.1.1.dist-info/WHEEL
annotation_validation-0.1.1.dist-info/top_level.txt
annotation_validation-0.1.1.dist-info/RECORD
