Metadata-Version: 1.1
Name: annotation-validation
Version: 0.1.1
Summary: Annotation Validation ensures type checking for function annotations.
Home-page: https://github.com/szuckerman/annotation_validation
Author: Sam Zuckerman
Author-email: sam.p.zuckerman@gmail.com
License: MIT license
Keywords: annotation_validation
Platform: UNKNOWN
Classifier: Development Status :: 2 - Pre-Alpha
Classifier: Intended Audience :: Developers
Classifier: License :: OSI Approved :: MIT License
Classifier: Natural Language :: English
Classifier: Programming Language :: Python :: 3.5
Classifier: Programming Language :: Python :: 3.6
Classifier: Programming Language :: Python :: 3.7
